cersys/__init__.py
cersys/_bindings.py
cersys/cersys_kernels.cl
cersys/core.py
cersys/io.py
cersys/libcersys.dylib
cersys/model.py
cersys/py.typed
cersys/sparse.py
cersys/tensor.py
cersys/training.py
cersys/utils.py
cersys-0.0.2.dist-info/LICENSE
cersys-0.0.2.dist-info/METADATA
cersys-0.0.2.dist-info/WHEEL
cersys-0.0.2.dist-info/top_level.txt
cersys-0.0.2.dist-info/RECORD
