Metadata-Version: 2.2
Name: cersys
Version: 0.0.2
Summary: High-performance recommender systems library with GPU acceleration
Author: Matteo Caviglia
License: MIT
Project-URL: Repository, https://github.com/22cav/cersys
Keywords: recommender-systems,machine-learning,deep-learning,collaborative-filtering,matrix-factorization,gpu,opencl
Classifier: Development Status :: 1 - Planning
Classifier: Intended Audience :: Developers
Classifier: Intended Audience :: Science/Research
Classifier: Operating System :: MacOS :: MacOS X
Classifier: Operating System :: POSIX :: Linux
Classifier: Programming Language :: Python :: 3
Classifier: Programming Language :: Python :: 3.10
Classifier: Programming Language :: Python :: 3.11
Classifier: Programming Language :: Python :: 3.12
Classifier: Programming Language :: Python :: 3.13
Classifier: Topic :: Scientific/Engineering :: Artificial Intelligence
Requires-Python: >=3.10
License-File: LICENSE
Requires-Dist: numpy>=1.19.0
Provides-Extra: dev
Requires-Dist: pytest>=6.0; extra == "dev"
Requires-Dist: pytest-cov; extra == "dev"
Requires-Dist: scipy>=1.5.0; extra == "dev"
Requires-Dist: pandas>=1.0.0; extra == "dev"
Provides-Extra: scipy
Requires-Dist: scipy>=1.5.0; extra == "scipy"
Provides-Extra: all
Requires-Dist: scipy>=1.5.0; extra == "all"
Requires-Dist: pandas>=1.0.0; extra == "all"
Requires-Dist: scikit-learn>=0.24.0; extra == "all"
